[{"time": 1745393070.9200695, "description": "High memory usage: 80.2%", "context": {}}, {"time": 1745393071.9219997, "description": "High memory usage: 80.2%", "context": {}}, {"time": 1745393073.0369484, "description": "High memory usage: 80.3%", "context": {}}, {"time": 1745393074.0388474, "description": "High memory usage: 80.3%", "context": {}}, {"time": 1745393075.085223, "description": "High memory usage: 80.4%", "context": {}}, {"time": 1745393076.0864568, "description": "High memory usage: 80.5%", "context": {}}, {"time": 1745393077.0883017, "description": "High memory usage: 80.7%", "context": {}}, {"time": 1745393078.0908842, "description": "High memory usage: 80.8%", "context": {}}, {"time": 1745393079.093533, "description": "High memory usage: 80.8%", "context": {}}, {"time": 1745393080.0951335, "description": "High memory usage: 80.8%", "context": {}}, {"time": 1745393081.0963826, "description": "High memory usage: 81.0%", "context": {}}, {"time": 1745393082.1028283, "description": "High memory usage: 81.2%", "context": {}}, {"time": 1745393083.153319, "description": "High memory usage: 81.1%", "context": {}}, {"time": 1745393084.1553643, "description": "High memory usage: 81.2%", "context": {}}, {"time": 1745393085.1572647, "description": "High memory usage: 81.2%", "context": {}}, {"time": 1745393086.1595104, "description": "High memory usage: 81.4%", "context": {}}, {"time": 1745393087.2090604, "description": "High memory usage: 81.5%", "context": {}}, {"time": 1745393088.215838, "description": "High memory usage: 81.5%", "context": {}}, {"time": 1745393089.330463, "description": "High memory usage: 81.6%", "context": {}}, {"time": 1745393090.3325863, "description": "High memory usage: 81.6%", "context": {}}, {"time": 1745393091.334681, "description": "High memory usage: 81.9%", "context": {}}, {"time": 1745393092.3943481, "description": "High memory usage: 82.0%", "context": {}}, {"time": 1745393093.4036896, "description": "High memory usage: 82.0%", "context": {}}, {"time": 1745393094.4073784, "description": "High memory usage: 82.1%", "context": {}}, {"time": 1745393095.40945, "description": "High memory usage: 82.1%", "context": {}}, {"time": 1745393096.4162607, "description": "High memory usage: 82.3%", "context": {}}, {"time": 1745393097.4183302, "description": "High memory usage: 82.3%", "context": {}}, {"time": 1745393098.437384, "description": "High memory usage: 82.4%", "context": {}}, {"time": 1745393099.4396932, "description": "High memory usage: 82.4%", "context": {}}, {"time": 1745393100.4416924, "description": "High memory usage: 82.5%", "context": {}}, {"time": 1745393101.4643114, "description": "High memory usage: 82.7%", "context": {}}, {"time": 1745393102.4671292, "description": "High memory usage: 82.8%", "context": {}}, {"time": 1745393103.4693186, "description": "High memory usage: 82.8%", "context": {}}, {"time": 1745393104.4713871, "description": "High memory usage: 82.8%", "context": {}}, {"time": 1745393105.5082233, "description": "High memory usage: 82.8%", "context": {}}, {"time": 1745393106.5184042, "description": "High memory usage: 83.1%", "context": {}}, {"time": 1745393107.5205984, "description": "High memory usage: 83.2%", "context": {}}, {"time": 1745393108.522724, "description": "High memory usage: 83.2%", "context": {}}, {"time": 1745393109.5250206, "description": "High memory usage: 83.2%", "context": {}}, {"time": 1745393110.5275936, "description": "High memory usage: 83.3%", "context": {}}, {"time": 1745393111.5298707, "description": "High memory usage: 83.6%", "context": {}}, {"time": 1745393112.5320413, "description": "High memory usage: 83.6%", "context": {}}, {"time": 1745393113.56571, "description": "High memory usage: 83.6%", "context": {}}, {"time": 1745393114.5697057, "description": "High memory usage: 83.7%", "context": {}}, {"time": 1745393115.5719576, "description": "High memory usage: 83.8%", "context": {}}, {"time": 1745393116.5740623, "description": "High memory usage: 84.0%", "context": {}}, {"time": 1745393117.5821202, "description": "High memory usage: 84.0%", "context": {}}, {"time": 1745393118.5834482, "description": "High memory usage: 84.1%", "context": {}}, {"time": 1745393119.6395197, "description": "High memory usage: 84.2%", "context": {}}, {"time": 1745393120.6416748, "description": "High memory usage: 84.2%", "context": {}}, {"time": 1745393121.643878, "description": "High memory usage: 84.6%", "context": {}}, {"time": 1745393122.6463783, "description": "High memory usage: 84.5%", "context": {}}, {"time": 1745393123.65614, "description": "High memory usage: 84.6%", "context": {}}, {"time": 1745393124.6583965, "description": "High memory usage: 84.6%", "context": {}}, {"time": 1745393125.6605837, "description": "High memory usage: 84.7%", "context": {}}, {"time": 1745393126.680426, "description": "High memory usage: 84.9%", "context": {}}, {"time": 1745393127.6865406, "description": "High memory usage: 85.0%", "context": {}}, {"time": 1745393128.6884172, "description": "High memory usage: 85.0%", "context": {}}, {"time": 1745393129.6906335, "description": "High memory usage: 85.0%", "context": {}}, {"time": 1745393130.709014, "description": "High memory usage: 85.3%", "context": {}}, {"time": 1745393131.7112596, "description": "High memory usage: 85.4%", "context": {}}, {"time": 1745393132.7289677, "description": "High memory usage: 85.4%", "context": {}}, {"time": 1745393133.7311273, "description": "High memory usage: 85.5%", "context": {}}, {"time": 1745393134.7337797, "description": "High memory usage: 85.5%", "context": {}}, {"time": 1745393135.7378852, "description": "High memory usage: 85.5%", "context": {}}, {"time": 1745393136.7505336, "description": "High memory usage: 85.8%", "context": {}}, {"time": 1745393137.753227, "description": "High memory usage: 85.8%", "context": {}}, {"time": 1745393138.7558095, "description": "High memory usage: 85.9%", "context": {}}, {"time": 1745393139.803255, "description": "High memory usage: 85.9%", "context": {}}, {"time": 1745393140.8089492, "description": "High memory usage: 86.0%", "context": {}}, {"time": 1745393141.8114436, "description": "High memory usage: 86.2%", "context": {}}, {"time": 1745393142.813688, "description": "High memory usage: 86.3%", "context": {}}, {"time": 1745393143.8480422, "description": "High memory usage: 86.3%", "context": {}}, {"time": 1745393144.8499298, "description": "High memory usage: 86.4%", "context": {}}, {"time": 1745393145.903591, "description": "High memory usage: 86.4%", "context": {}}, {"time": 1745393146.9060035, "description": "High memory usage: 86.8%", "context": {}}, {"time": 1745393147.9083064, "description": "High memory usage: 86.7%", "context": {}}, {"time": 1745393148.930803, "description": "High memory usage: 86.8%", "context": {}}, {"time": 1745393149.9383726, "description": "High memory usage: 86.8%", "context": {}}, {"time": 1745393150.940901, "description": "High memory usage: 86.8%", "context": {}}, {"time": 1745393151.9433236, "description": "High memory usage: 87.1%", "context": {}}, {"time": 1745393153.0422277, "description": "High memory usage: 87.1%", "context": {}}, {"time": 1745393154.0508368, "description": "High memory usage: 87.2%", "context": {}}, {"time": 1745393155.0534785, "description": "High memory usage: 87.3%", "context": {}}, {"time": 1745393156.0559018, "description": "High memory usage: 87.2%", "context": {}}, {"time": 1745393157.0678215, "description": "High memory usage: 87.4%", "context": {}}, {"time": 1745393158.070036, "description": "High memory usage: 87.5%", "context": {}}, {"time": 1745393159.0725513, "description": "High memory usage: 87.5%", "context": {}}, {"time": 1745393160.0749834, "description": "High memory usage: 87.6%", "context": {}}, {"time": 1745393161.124323, "description": "High memory usage: 87.6%", "context": {}}, {"time": 1745393162.134824, "description": "High memory usage: 87.9%", "context": {}}, {"time": 1745393163.137555, "description": "High memory usage: 87.9%", "context": {}}, {"time": 1745393164.139962, "description": "High memory usage: 87.9%", "context": {}}, {"time": 1745393165.1550782, "description": "High memory usage: 87.9%", "context": {}}, {"time": 1745393166.1573133, "description": "High memory usage: 88.0%", "context": {}}, {"time": 1745393167.2079406, "description": "High memory usage: 88.1%", "context": {}}, {"time": 1745393168.2104747, "description": "High memory usage: 88.2%", "context": {}}, {"time": 1745393169.2130241, "description": "High memory usage: 88.3%", "context": {}}, {"time": 1745393170.2179732, "description": "High memory usage: 88.4%", "context": {}}, {"time": 1745393171.2264292, "description": "High memory usage: 88.4%", "context": {}}, {"time": 1745393172.2290514, "description": "High memory usage: 88.6%", "context": {}}, {"time": 1745393173.2317126, "description": "High memory usage: 88.7%", "context": {}}, {"time": 1745393174.2949483, "description": "High memory usage: 88.7%", "context": {}}, {"time": 1745393175.3010035, "description": "High memory usage: 88.7%", "context": {}}, {"time": 1745393176.303332, "description": "High memory usage: 88.9%", "context": {}}, {"time": 1745393177.3060348, "description": "High memory usage: 89.0%", "context": {}}, {"time": 1745393178.3523088, "description": "High memory usage: 89.1%", "context": {}}, {"time": 1745393179.3551254, "description": "High memory usage: 89.1%", "context": {}}, {"time": 1745393180.4133272, "description": "High memory usage: 89.1%", "context": {}}, {"time": 1745393181.4153523, "description": "High memory usage: 89.4%", "context": {}}, {"time": 1745393182.4179895, "description": "High memory usage: 89.4%", "context": {}}, {"time": 1745393183.4242156, "description": "High memory usage: 89.5%", "context": {}}, {"time": 1745393184.4274719, "description": "High memory usage: 89.5%", "context": {}}, {"time": 1745393185.4295814, "description": "High memory usage: 89.7%", "context": {}}, {"time": 1745393186.432829, "description": "High memory usage: 90.0%", "context": {}}, {"time": 1745393187.435738, "description": "High memory usage: 90.0%", "context": {}}, {"time": 1745393188.451479, "description": "High memory usage: 90.0%", "context": {}}, {"time": 1745393189.4547524, "description": "High memory usage: 90.0%", "context": {}}, {"time": 1745393190.4564013, "description": "High memory usage: 90.0%", "context": {}}, {"time": 1745393191.4600372, "description": "High memory usage: 90.1%", "context": {}}, {"time": 1745393192.463172, "description": "High memory usage: 90.1%", "context": {}}, {"time": 1745393198.4872155, "description": "High memory usage: 90.3%", "context": {}}, {"time": 1745393199.4894772, "description": "High memory usage: 90.3%", "context": {}}, {"time": 1745393200.492276, "description": "High memory usage: 90.3%", "context": {}}, {"time": 1745396041.567912, "description": "High CPU usage: 82.6%", "context": {}}]